Sandbox/adder.v
`timescale 1ns / 100ps

module adder (
    input clk,
    input rst,
    input [31:0] in,
    output [31:0] out
);
    reg [31:0] acc;

    assign out = in + acc;

    always @(posedge clk) begin
        if (rst) begin
            acc <= 0;
        end
        else begin
            acc <= out;
        end
    end
endmodule

Sandbox/adder_tb.v
`timescale 1ns / 100ps

module Adder_tb();
    reg [31:0] in;
    reg clk;
    reg rst;
    wire  [31:0] out;

    adder adderU (.clk(clk), .rst(rst), .in(in), .out(out));
    integer PASSED, FAILED;

    initial begin
        clk = 0;
        forever
            #5 clk = ~clk;
    end

    initial begin
        $dumpfile("waveform.vcd");
        $dumpvars(0, Adder_tb);
    end

    initial begin
        PASSED = 0;
        FAILED = 0;
        rst = 1;
        # 16
        rst = 0;
        in = 32'd1;
        #1
        if (out == 32'd1)   PASSED = PASSED + 1;
        else                FAILED = FAILED + 1;
        #9
        in = 32'd2;
        #1
        if(out == 32'd3)    PASSED = PASSED + 1;
        else                FAILED = FAILED + 1;
        #9
        in = 32'd5;
        #1
        if(out == 32'd8)    PASSED = PASSED + 1;
        else                FAILED = FAILED + 1;
        $display("PASSED: %d, FAILED: %d", PASSED, FAILED);
        $finish();
    end

endmodule

Sandbox/waveform.vcd
$date
	Sun Mar 29 04:01:09 2026
$end
$version
	Icarus Verilog
$end
$timescale
	100ps
$end
$scope module Adder_tb $end
$var wire 32 ! out [31:0] $end
$var reg 1 " clk $end
$var reg 32 # in [31:0] $end
$var reg 1 $ rst $end
$var integer 32 % FAILED [31:0] $end
$var integer 32 & PASSED [31:0] $end
$scope module adderU $end
$var wire 1 " clk $end
$var wire 32 ' in [31:0] $end
$var wire 1 $ rst $end
$var wire 32 ( out [31:0] $end
$var reg 32 ) acc [31:0] $end
$upscope $end
$upscope $end
$enddefinitions $end
$comment Show the parameter values. $end
$dumpall
$end
#0
$dumpvars
bx )
bx (
bx '
b0 &
b0 %
1$
bx #
0"
bx !
$end
#50
b0 )
1"
#100
0"
#150
1"
#160
b1 !
b1 (
b1 #
b1 '
0$
#170
b1 &
#200
0"
#250
b10 !
b10 (
b1 )
1"
#260
b11 !
b11 (
b10 #
b10 '
#270
b10 &
#300
0"
#350
b101 !
b101 (
b11 )
1"
#360
b1000 !
b1000 (
b101 #
b101 '
#370
b11 &
